math_randomseed/__init__.py
math_randomseed/cli.py
math_randomseed/math_randomseed.py
math_randomseed-0.2.3.dist-info/LICENSE
math_randomseed-0.2.3.dist-info/METADATA
math_randomseed-0.2.3.dist-info/WHEEL
math_randomseed-0.2.3.dist-info/entry_points.txt
math_randomseed-0.2.3.dist-info/top_level.txt
math_randomseed-0.2.3.dist-info/RECORD
