Metadata-Version: 2.1
Name: math-randomseed
Version: 0.2.3
Summary: A Python package providing basic math operations and a sprinkle of humor with random math facts and jokes.
Author-email: Your Name <your@email.com>
License: GNU GENERAL PUBLIC LICENSE
Project-URL: Homepage, https://github.com/software-students-fall2023/3-python-package-exercise-random-seed-2/tree/main
Keywords: math,operations,add,subtract,multiply,divide,get_math_fact
Classifier: Programming Language :: Python :: 3
Classifier: Programming Language :: Python :: 3 :: Only
Classifier: License :: OSI Approved :: MIT License
Classifier: Operating System :: OS Independent
Requires-Python: >=3.6
License-File: LICENSE
